aryahelpers/__init__.py
aryahelpers/app.py
aryahelpers/appconfig.py
aryahelpers/logmanager.py
aryahelpers/apiroutes/__init__.py
aryahelpers/apiroutes/aryaapis.py
aryahelpers/apiroutes/explanationapi.py
aryahelpers/aryatestbed/__init__.py
aryahelpers/aryatestbed/explaccess.py
aryahelpers/aryatestbed/testbed.py
aryahelpers/configuration/__init__.py
aryahelpers/configuration/config.helpers.json
aryahelpers/configuration/config.json
aryahelpers/data/QA_testbed_jobs.json
aryahelpers/data/__init__.py
aryahelpers/data/english_words.p
aryahelpers/joboperations/__init__.py
aryahelpers/joboperations/contenders.py
aryahelpers/joboperations/jobs.py
aryahelpers/utils/__init__.py
aryahelpers/utils/genericutils.py
aryahelpers/utils/helpersnippets.py
aryahelpers/utils/mysqlutils.py
aryahelpers/utils/textclean.py
aryahelpers-0.2.7.dist-info/METADATA
aryahelpers-0.2.7.dist-info/WHEEL
aryahelpers-0.2.7.dist-info/top_level.txt
aryahelpers-0.2.7.dist-info/RECORD
