Metadata-Version: 2.1
Name: aryahelpers
Version: 0.2.7
Summary: Arya Helpers Modules
Home-page: https://gitlab.com/aryacoreprojects/arya-helpers.git
Download-URL: https://gitlab.com/aryacoreprojects/arya-helpers
Author: Ratnadip Adhikari
Author-email: ratnadip.adhikari@leoforce.com
Keywords: utilities,arya,helper modules
Platform: any
Classifier: Development Status :: 4 - Beta
Classifier: Intended Audience :: Developers
Classifier: Operating System :: OS Independent
Classifier: Programming Language :: Python :: 3
Classifier: Topic :: Utilities
